deep_nlp/__init__.py
deep_nlp/framework.py
deep_nlp/model_wrapper.py
deep_nlp/utils.py
deep_nlp-0.0.1.data/scripts/extract_model
deep_nlp-0.0.1.dist-info/LICENSE
deep_nlp-0.0.1.dist-info/METADATA
deep_nlp-0.0.1.dist-info/WHEEL
deep_nlp-0.0.1.dist-info/top_level.txt
deep_nlp-0.0.1.dist-info/RECORD
