Metadata-Version: 2.1
Name: deep-nlp
Version: 0.0.1
Summary: Deep nlp library
Home-page: https://github.com/FabianBell/deepl_framework
Author: Fabian Bell
Author-email: fabianx.bell@gmail.com
License: MIT
Platform: UNKNOWN
Classifier: Programming Language :: Python :: 3
Classifier: License :: OSI Approved :: MIT License
Requires-Dist: torch (>=1.8.1)
Requires-Dist: pytorch-lightning (>=1.2.10)
Requires-Dist: mlflow (>=1.16.0)
Requires-Dist: transformers (>=4.5.1)
Requires-Dist: sentencepiece (>=0.1.95)
